azure/cognitiveservices/search/websearch/__init__.py
azure/cognitiveservices/search/websearch/_configuration.py
azure/cognitiveservices/search/websearch/_web_search_client.py
azure/cognitiveservices/search/websearch/py.typed
azure/cognitiveservices/search/websearch/version.py
azure/cognitiveservices/search/websearch/models/__init__.py
azure/cognitiveservices/search/websearch/models/_models.py
azure/cognitiveservices/search/websearch/models/_models_py3.py
azure/cognitiveservices/search/websearch/models/_web_search_client_enums.py
azure/cognitiveservices/search/websearch/operations/__init__.py
azure/cognitiveservices/search/websearch/operations/_web_operations.py
azure_cognitiveservices_search_websearch-2.0.1.dist-info/LICENSE
azure_cognitiveservices_search_websearch-2.0.1.dist-info/METADATA
azure_cognitiveservices_search_websearch-2.0.1.dist-info/WHEEL
azure_cognitiveservices_search_websearch-2.0.1.dist-info/top_level.txt
azure_cognitiveservices_search_websearch-2.0.1.dist-info/RECORD
